webhooktesting/__init__.py
webhooktesting/_version.py
webhooktesting/main.py
webhooktesting/routes/__init__.py
webhooktesting/routes/core.py
webhooktesting/routes/diagnostics.py
webhooktesting/schemas/__init__.py
webhooktesting/schemas/response.py
webhooktesting/utils/__init__.py
webhooktesting/utils/lru_list.py
webhook_testing-0.9.0.dist-info/LICENSE
webhook_testing-0.9.0.dist-info/METADATA
webhook_testing-0.9.0.dist-info/WHEEL
webhook_testing-0.9.0.dist-info/top_level.txt
webhook_testing-0.9.0.dist-info/RECORD
